Workbook

Sheet CMB
C3: CELULARES MB VALPA | E3: RELACION DE EQUIPOS VENDIDOS
C4: Valparaíso Zacatecas México
C5: Cel: 457 103 2866
B8: CODIGO | C8: DESCRIPCIÓN | D8: $ SUGERIDO | E8: IMEI | F8: FECHA DE VENTA | G8: VENTA FINAL | H8: COSTO | I8: OTROS COSTOS | J8: UTILIDAD | K8: COMENTARIOS
B9: MBC01 | C9: SAMSUNG GALAXY M15 | D9: 1800 | G9: 1800 | H9: 1300 | I9: 100 | J9: =D9-H9-I9 -> 400
B10: MBC02 | C10: OPPO A57 | D10: 1500 | G10: 1400 | H10: 1000 | I10: 100 | J10: =G10-H10-I10 -> 300
B11: MBC03 | C11: ZTE BLADE V70 MAX | D11: 2100 | G11: 2100 | H11: 1600
B12: MBC04 | C12: GALAXY A06 | D12: 1500 | G12: 1500 | H12: 1000 | I12: 100 | J12: =G12-H12-I12 -> 400
B13: MBC04 | C13: APPLE IPHONE 17PRO MAX NUEVO | D13: 26800 | G13: 26800 | H13: 25200 | I13: 100 | J13: =G13-H13-I13 -> 1500
B14: MBC05 | C14: MOTO G15 | D14: 1300 | J14: =G14-H14-I14 -> 0
B15: MBC06 | J15: =G15-H15-I15 -> 0
J16: =G16-H16-I16 -> 0
J17: =G17-H17-I17 -> 0
J18: =G18-H18-I18 -> 0
J19: =G19-H19-I19 -> 0
J20: =G20-H20-I20 -> 0
J21: =G21-H21-I21 -> 0
J22: =G22-H22-I22 -> 0
J23: =G23-H23-I23 -> 0
J24: =G24-H24-I24 -> 0
J25: =G25-H25-I25 -> 0
J26: =G26-H26-I26 -> 0
J27: =G27-H27-I27 -> 0
... J37: =G37-H37-I37 -> 0

Sheet BADA
B5: Precios
B7: Descripcion
B8: Concepto | C8: Descripcipon | D8: Cantidad | E8: Inversion | F8: Costo | G8: Precio Mayoreo | H8: Precio Men | I8: Marketplace | J8: G1 | K8: Competencia 1 | L8: Competencia 2 | M8: Precios MBM | N8: Venta MBM | O8: Venta Men | P8: FOTO
A9: 1 | B9: B V8 USB | C9: CABLE USB NORMAL TRENZADO SIN CAJA | D9: 20 | E9: 5 | F9: =D9*E9 -> 100 | G9: 13 | H9: 20 | K9: 40 | L9: 80 | M9: =G9 -> 13 | N9: =D9*G9-(D9*E9) -> 160 | O9: =D9*H9-(D9*E9) -> 300
A10: 2 | B10: B USB - C | C10: CABLE USB TIPO C TRENZADO SIN CAJA | D10: 40 | E10: 8 | F10: =D10*E10 -> 320 | G10: 15 | H10: 25 | M10: =G10 -> 15 | N10: =D10*G10-(D10*E10) -> 280 | O10: =D10*H10-(D10*E10) -> 680
A11: 3 | B11: P USB - C Mot | C11: CABLE ORIGINAL USB A C MOTOROLA | D11: 20 | E11: 20 | F11: =D11*E11 -> 400 | G11: 30 | H11: 60 | K11: 50 | L11: 100 | M11: =G11 -> 30 | N11: =D11*G11-(D11*E11) -> 200 | O11: =D11*H11-(D11*E11) -> 800
A12: 4 | B12: P C-C Sam | C12: CABLE ORIGINAL TIPO C-C SAMSUNG | D12: 20 | E12: 20 | F12: =D12*E12 -> 400 | G12: 40 | H12: 80 | K12: 40 | L12: 100 | M12: =G12 -> 40 | N12: =D12*G12-(D12*E12) -> 400 | O12: =D12*H12-(D12*E12) -> 1200
A13: 5 | B13: P C-C iP | C13: CABLE ORIGINAL IPHONE TIPO C | D13: 30 | E13: 11 | F13: =D13*E13 -> 330 | G13: 40 | H13: 70 | M13: =G13 -> 40 | N13: =D13*G13-(D13*E13) -> 870 | O13: =D13*H13-(D13*E13) -> 1770
A14: 6 | B14: B iPh L | C14: CABLE IPHONE C A LIGTHNING | D14: 40 | E14: 5.5 | F14: =D14*E14 -> 220 | G14: 20 | H14: 35 | K14: 30 | L14: 100 | M14: =G14 -> 20 | N14: =D14*G14-(D14*E14) -> 580 | O14: =D14*H14-(D14*E14) -> 1180
A15: 7 | B15: Cubo iPhone | C15: CUBO 20W ORIGINAL IPHONE | D15: 50 | E15: 20 | F15: =D15*E15 -> 1000 | G15: 40 | H15: 80 | K15: - | L15: 150 | M15: =G15 -> 40 | N15: =D15*G15-(D15*E15) -> 1000 | O15: =D15*H15-(D15*E15) -> 3000
A16: 8 | B16: P iPh C-L | C16: CARGDOR IPHONE ORIGINAL C-LIGTH | D16: 15 | E16: 29 | F16: =D16*E16 -> 435 | G16: 40 | H16: 80 | L16: 30 | M16: =G16 -> 40 | N16: =D16*G16-(D16*E16) -> 165 | O16: =D16*H16-(D16*E16) -> 765
A17: 9 | B17: Cubo medio | C17: CARGADOR GEN12W USB + C Sin CAJA | D17: 52 | E17: 20 | F17: =D17*E17 -> 1040 | G17: 30 | H17: 50 | M17: =G17 -> 30 | N17: =D17*G17-(D17*E17) -> 520 | O17: =D17*H17-(D17*E17) -> 1560
A18: 10 | B18: B Charg Comp C | C18: CARGADOR COMPLETO 1 HORA TIPO C | D18: 10 | E18: 28 | F18: =D18*E18 -> 280 | G18: 40 | H18: 50 | K18: 45 | L18: 150 | M18: =G18 -> 40 | N18: =D18*G18-(D18*E18) -> 120 | O18: =D18*H18-(D18*E18) -> 220
A19: 11 | B19: P Charg comp C | C19: CARGADOR ORIGINAL SAMSUNG USB-C | D19: 10 | E19: 45 | F19: =D19*E19 -> 450 | G19: 60 | H19: 130 | M19: =G19 -> 60 | N19: =D19*G19-(D19*E19) -> 150 | O19: =D19*H19-(D19*E19) -> 850
A20: 12 | B20: B Charg iPhone L | C20: CARGADOR ECONOMICO IPHONE | D20: 40 | F20: =D20*E20 -> 0 | G20: 15 | L20: 250 | M20: =G20 -> 15 | N20: =D20*G20-(D20*E20) -> 600 | O20: =D20*H20-(D20*E20) -> 0
A21: 13 | B21: P Charg iPhone C-L | C21: CARGADOR ORIGINAL IPHONE LIGTHNING | D21: 10 | E21: 31 | F21: =D21*E21 -> 310 | G21: 45 | H21: 100 | M21: =G21 -> 45 | N21: =D21*G21-(D21*E21) -> 140 | O21: =D21*H21-(D21*E21) -> 690
A22: 14 | B22: Bocina 01 | C22: BOCINA GENERICA CHICA | D22: 2 | E22: 45 | F22: =D22*E22 -> 90 | G22: 70 | H22: 100 | M22: =G22 -> 70 | N22: =D22*G22-(D22*E22) -> 50 | O22: =D22*H22-(D22*E22) -> 110
A23: 15 | B23: Bocina 02 | C23: BOCINA GENERICA MEDIANA | D23: 2 | E23: 80 | F23: =D23*E23 -> 160 | G23: 100 | H23: 200 | M23: =G23 -> 100 | N23: =D23*G23-(D23*E23) -> 40 | O23: =D23*H23-(D23*E23) -> 240
A24: 16 | B24: Audifono Eco | C24: AUDIFONOS BLUETOOTH GENERICOS | D24: 18 | E24: 21 | F24: =D24*E24 -> 378 | G24: 60 | H24: 100 | L24: 200 | M24: =G24 -> 60 | N24: =D24*G24-(D24*E24) -> 702 | O24: =D24*H24-(D24*E24) -> 1422
A25: 17 | B25: Airpods Pro 3 | C25: AIRPODS PRO 3 CANCELACION GPS #SERIE | D25: 50 | E25: 150 | F25: =D25*E25 -> 7500 | G25: 250 | H25: 350 | L25: 500 | M25: =G25 -> 250 | N25: =(D25*M25)-(D25*E25) -> 5000
A26: 18 | B26: Adaptador 4 en 1 | C26: ADAPTADOR CABLE 4 EN 1 | D26: 10 | E26: 17 | F26: =D26*E26 -> 170 | G26: 45 | H26: 80 | M26: =G26 -> 45 | N26: =D26*G26-(D26*E26) -> 280 | O26: =D26*H26-(D26*E26) -> 630
A27: 19 | B27: Bluetooth Aux | C27: AUXILIAR BLUETOOTH | D27: 3 | E27: 18 | F27: =D27*E27 -> 54 | G27: 25 | H27: 60 | K27: 150 | L27: 250 | M27: =G27 -> 25 | N27: =D27*G27-(D27*E27) -> 21 | O27: =D27*H27-(D27*E27) -> 126
A28: 20 | B28: Bocina go 4 | C28: BOCINA JBL CHICA GO 4 | D28: 12 | E28: 95 | F28: =D28*E28 -> 1140 | G28: 150 | H28: 250 | L28: 190 | M28: =G28 -> 150 | N28: =D28*G28-(D28*E28) -> 660 | O28: =D28*H28-(D28*E28) -> 1860
A29: 21 | B29: Bocina lip 6 | C29: BOCINA JBL GRANDE FLIP 6 | D29: 5 | E29: 210 | F29: =D29*E29 -> 1050 | G29: 250 | H29: 500 | K29: 350 | L29: 350 | M29: =G29 -> 250 | N29: =D29*G29-(D29*E29) -> 200 | O29: =D29*H29-(D29*E29) -> 1450
A30: 22 | B30: Car Charg | C30: CARGADOR CARRO | D30: 5 | E30: 5 | F30: =D30*E30 -> 25 | G30: 15 | H30: 55 | K30: 45 | L30: 120 | M30: =G30 -> 15 | N30: =D30*G30-(D30*E30) -> 50 | O30: =D30*H30-(D30*E30) -> 250
A31: 23 | B31: Transmisor | C31: TRANSMISOR DE CARRO | D31: 5 | E31: 45 | F31: =D31*E31 -> 225 | G31: 60 | H31: 100 | K31: 175 | L31: 280 | M31: =G31 -> 60 | N31: =D31*G31-(D31*E31) -> 75 | O31: =D31*H31-(D31*E31) -> 275
A32: 24 | B32: Powerbank | C32: POWERBANK 20,000 Ma | D32: 5 | E32: 55 | F32: =D32*E32 -> 275 | G32: 80 | H32: 150 | M32: =G32 -> 80 | N32: =D32*G32-(D32*E32) -> 125 | O32: =D32*H32-(D32*E32) -> 475
A33: 25 | B33: Smart Watch 1 | C33: RELOJ INTELIGENTE | D33: 2 | E33: 80 | F33: =D33*E33 -> 160 | G33: 120 | H33: 180 | M33: =G33 -> 120 | N33: =D33*G33-(D33*E33) -> 80 | O33: =D33*H33-(D33*E33) -> 200
A34: 26 | B34: Smart watch 2 | C34: RELOJ INTELIGENTE COMBO | D34: 2 | E34: 158 | F34: =D34*E34 -> 316 | G34: 200 | H34: 300 | M34: =G34 -> 200 | N34: =D34*G34-(D34*E34) -> 84 | O34: =D34*H34-(D34*E34) -> 284
B35: TOTAL | D35: 453 | F35: =SUM(F9:F34) -> 16828 | G35: 1833 | H35: 3265 | N35: =SUM(N9:N34) -> 12552 | O35: =D35*H35-(D35*E35) -> 1479045
B37: EXTRA
B38: Playera | C38: Playera Selección Mexicana Verde Mundial | D38: 9 | E38: 60 | F38: =D38*E38 -> 540 | G38: 100 | H38: 150
B39: Audif Skullc | C39: SKULLCANDY TWS7 BLUET | D39: 45 | G39: 80
B40: Audif Earpods B | C40: EARPODS GENERICOS | D40: 45 | G40: 60
B41: Audif Buytiti 125 | C41: AUDIFONOS BLUETOOTH | D41: 45 | G41: 60
B42: Audif Buy W133 | C42: AUDIFONOS BLUETOOTH | D42: 45 | G42: 60
B43: Airpods Pro 2da | C43: AIRPODS PRO 3 MAXIMA CALIDAD | D43: 130 | G43: 200
B44: Airpods 4ta | C44: AIRPODS 4 MAXIMA CALIDAD | D44: 115 | G44: 200

Sheet DESARROLLO
B5: Objetivo
B6: Crear una red de distribución de accesorios tecnológicos en donde aún no se tiene presencia de grandes competidores
B8: Visión
B9: Convertirse en el mayor distribuidor de accesorios tecnológicos de la región
B11: Mision
B12: Crear una red de distribución eficaz, de bajo costo y con el mayor rango de utilidad posible, llegar a donde nadie más llega
B14: Plan
B15: Identificación de tiendas que ya cuenta con venta de abarrotes, menesteres o similares los cuales puedan comercializar nuestros productos
B17: Ubicaciones clave
B18: Ruta | C18: Cliente | D18: Valpa | F18: Huej
B19: Lob1 | C19: 2 | D19: El Tejujan | E19: 0 | F19: Potrero de gallegos | G19: 0
B20: Ciana de abajo | C20: 0 | D20: El resbalon | E20: 0 | F20: El Astillero | G20: 0
B21: Ciana de arriba | C21: 1 | D21: Valles del Sol | E21: 0 | F21: La Florida | G21: 3
B22: Colonia del Vergel | C22: 2 | D22: Santa Rita | E22: 0 | F22: San Martín | G22: 2
B23: Xoconostle | C23: 0 | D23: Zapata | E23: 0 | F23: Pastores | G23: 0
D24: Atotonilco | E24: 3
B25: Mala Noche | C25: 0 | D25: Las Cumbres | E25: 0
B26: Lobatos | C26: 3 | D26: Ranchito de la cruz | E26: 0
B27: Caracoles | C27: 1 | D27: Madero | E27: 0
B28: Peñitas | C28: 1 | D28: El Capulín | E28: 1
B29: El Salitre | C29: 1 | G29: Venta | H29: Total | J29: Flete | K29: Ruta | L29: Gran Total
B30: San Mateo | C30: 3 | E30: Total 1 | F30: 7 | G30: =J68 -> 547.5 | H30: =J68*F30 -> 3832.5 | K30: 1000 | L30: =H33-G33-J30-K30 -> 9743
B31: Jamaica | C31: 0 | E31: Total 2 | F31: 3 | G31: =J69 -> 1595.5 | H31: =J69*F31 -> 4786.5
B32: San Miguel | C32: 1 | E32: Total 3 | F32: 3 | G32: =J70 -> 2133.5 | H32: =J70*F32 -> 6400.5
B33: Mimbres | C33: 1 | E33: Total | F33: =SUM(F30:F32) -> 13 | G33: =SUM(G30:G32) -> 4276.5 | H33: =SUM(H30:H32) -> 15019.5
B34: Trojes | C34: 1
B37: 1 | C37: 7 | D37: 2 | E37: 3 | F37: 3 | G37: 3 | H37: Arranque operaciones
B38: Paquete starter | C38: Cantidad | D38: Paquete Avanzado | E38: Cantidad | F38: Paquete prémiere | G38: Cantidad | H38: Cantidad | I38: COMPARACI | J38: Precio | K38: Total
B39: =D39 -> B V8 USB | C39: 1 | D39: =F39 -> B V8 USB | E39: 2 | F39: =BADA!B9 -> B V8 USB | G39: 2 | H39: =BADA!D9 -> 20 | I39: =SUM(C39*C$37+E39*E$37+G39*G$37) -> 19 | J39: =BADA!E9 -> 5 | K39: =J39*H39 -> 100
B40: =D40 -> B USB - C | C40: 3 | D40: =F40 -> B USB - C | E40: 3 | F40: =BADA!B10 -> B USB - C | G40: 3 | H40: =BADA!D10 -> 40 | I40: =SUM(C40*C$37+E40*E$37+G40*G$37) -> 39 | J40: =BADA!E10 -> 8 | K40: =J40*H40 -> 320
B41: =D41 -> P USB - C Mot | C41: 1 | D41: =F41 -> P USB - C Mot | E41: 2 | F41: =BADA!B11 -> P USB - C Mot | G41: 2 | H41: =BADA!D11 -> 20 | I41: =SUM(C41*C$37+E41*E$37+G41*G$37) -> 19 | J41: =BADA!E11 -> 20 | K41: =J41*H41 -> 400
B42: =D42 -> P C-C Sam | C42: 1 | D42: =F42 -> P C-C Sam | E42: 2 | F42: =BADA!B12 -> P C-C Sam | G42: 2 | H42: =BADA!D12 -> 20 | I42: =SUM(C42*C$37+E42*E$37+G42*G$37) -> 19 | J42: =BADA!E12 -> 20 | K42: =J42*H42 -> 400
B43: =D43 -> P C-C iP | C43: 2 | D43: =F43 -> P C-C iP | E43: 2 | F43: =BADA!B13 -> P C-C iP | G43: 3 | H43: =BADA!D13 -> 30 | I43: =SUM(C43*C$37+E43*E$37+G43*G$37) -> 29 | J43: =BADA!E13 -> 11 | K43: =J43*H43 -> 330
B44: =D44 -> B iPh L | C44: 3 | D44: =F44 -> B iPh L | E44: 3 | F44: =BADA!B14 -> B iPh L | G44: 3 | H44: =BADA!D14 -> 40 | I44: =SUM(C44*C$37+E44*E$37+G44*G$37) -> 39 | J44: =BADA!E14 -> 5.5 | K44: =J44*H44 -> 220
B45: =D45 -> Cubo iPhone | C45: 3 | D45: =F45 -> Cubo iPhone | E45: 1 | F45: =BADA!B15 -> Cubo iPhone | G45: 2 | H45: =BADA!D15 -> 50 | I45: =SUM(C45*C$37+E45*E$37+G45*G$37) -> 30 | J45: =BADA!E15 -> 20 | K45: =J45*H45 -> 1000
B46: =D46 -> P iPh C-L | D46: =F46 -> P iPh C-L | E46: 2 | F46: =BADA!B16 -> P iPh C-L | G46: 1 | H46: =BADA!D16 -> 15 | J46: =BADA!E16 -> 29 | K46: =J46*H46 -> 435
B47: =D47 -> Cubo medio | C47: 4 | D47: =F47 -> Cubo medio | E47: 3 | F47: =BADA!B17 -> Cubo medio | G47: 4 | H47: =BADA!D17 -> 52 | I47: =SUM(C47*C$37+E47*E$37+G47*G$37) -> 49 | J47: =BADA!E17 -> 20 | K47: =J47*H47 -> 1040
D48: =F48 -> B Charg Comp C | E48: 1 | F48: =BADA!B18 -> B Charg Comp C | G48: 2 | H48: =BADA!D18 -> 10 | I48: =SUM(C48*C$37+E48*E$37+G48*G$37) -> 9 | J48: =BADA!E18 -> 28 | K48: =J48*H48 -> 280
D49: =F49 -> P Charg comp C | E49: 1 | F49: =BADA!B19 -> P Charg comp C | G49: 2 | H49: =BADA!D19 -> 10 | I49: =SUM(C49*C$37+E49*E$37+G49*G$37) -> 9 | J49: =BADA!E19 -> 45 | K49: =J49*H49 -> 450
D50: =F50 -> B Charg iPhone L | E50: 2 | F50: =BADA!B20 -> B Charg iPhone L | G50: 3 | H50: =BADA!D20 -> 40 | I50: =SUM(C50*C$37+E50*E$37+G50*G$37) -> 15 | J50: =BADA!E20 | K50: =J50*H50 -> 0
D51: =F51 -> P Charg iPhone C-L | E51: 1 | F51: =BADA!B21 -> P Charg iPhone C-L | G51: 2 | H51: =BADA!D21 -> 10 | I51: =SUM(C51*C$37+E51*E$37+G51*G$37) -> 9 | J51: =BADA!E21 -> 31 | K51: =J51*H51 -> 310
D52: =F52 -> Bocina 01 | F52: =BADA!B22 -> Bocina 01 | G52: 1 | H52: =BADA!D22 -> 2 | I52: =SUM(C52*C$37+E52*E$37+G52*G$37) -> 3 | J52: =BADA!E22 -> 45 | K52: =J52*H52 -> 90
D53: =F53 -> Bocina 02 | F53: =BADA!B23 -> Bocina 02 | G53: 1 | H53: =BADA!D23 -> 2 | I53: =SUM(C53*C$37+E53*E$37+G53*G$37) -> 3 | J53: =BADA!E23 -> 80 | K53: =J53*H53 -> 160
D54: =F54 -> Audifono Eco | E54: 3 | F54: =BADA!B24 -> Audifono Eco | G54: 3 | H54: =BADA!D24 -> 18 | I54: =SUM(C54*C$37+E54*E$37+G54*G$37) -> 18 | J54: =BADA!E24 -> 21 | K54: =J54*H54 -> 378
D55: =F55 -> Airpods Pro 3 | E55: 3 | F55: =BADA!B25 -> Airpods Pro 3 | G55: 3 | H55: =BADA!D25 -> 50 | I55: =SUM(C55*C$37+E55*E$37+G55*G$37) -> 18 | J55: =BADA!E25 -> 150 | K55: =J55*H55 -> 7500
D56: =F56 -> Adaptador 4 en 1 | E56: 1 | F56: =BADA!B26 -> Adaptador 4 en 1 | G56: 1 | H56: =BADA!D26 -> 10 | I56: =SUM(C56*C$37+E56*E$37+G56*G$37) -> 6 | J56: =BADA!E26 -> 17 | K56: =J56*H56 -> 170
F57: =BADA!B27 -> Bluetooth Aux | G57: 1 | H57: =BADA!D27 -> 3 | I57: =SUM(C57*C$37+E57*E$37+G57*G$37) -> 3 | J57: =BADA!E27 -> 18 | K57: =J57*H57 -> 54
D58: =F58 -> Bocina go 4 | E58: 2 | F58: =BADA!B28 -> Bocina go 4 | G58: 2 | H58: =BADA!D28 -> 12 | I58: =SUM(C58*C$37+E58*E$37+G58*G$37) -> 12 | J58: =BADA!E28 -> 95 | K58: =J58*H58 -> 1140
D59: =F59 -> Bocina lip 6 | E59: 1 | F59: =BADA!B29 -> Bocina lip 6 | G59: 1 | H59: =BADA!D29 -> 5 | I59: =SUM(C59*C$37+E59*E$37+G59*G$37) -> 6 | J59: =BADA!E29 -> 210 | K59: =J59*H59 -> 1050
D60: =F60 -> Car Charg | E60: 1 | F60: =BADA!B30 -> Car Charg | G60: 1 | H60: =BADA!D30 -> 5 | I60: =SUM(C60*C$37+E60*E$37+G60*G$37) -> 6 | J60: =BADA!E30 -> 5 | K60: =J60*H60 -> 25
D61: =F61 -> Transmisor | E61: 1 | F61: =BADA!B31 -> Transmisor | G61: 1 | H61: =BADA!D31 -> 5 | I61: =SUM(C61*C$37+E61*E$37+G61*G$37) -> 6 | J61: =BADA!E31 -> 45 | K61: =J61*H61 -> 225
F62: =BADA!B32 -> Powerbank | G62: 1 | H62: =BADA!D32 -> 5 | I62: =SUM(C62*C$37+E62*E$37+G62*G$37) -> 3 | J62: =BADA!E32 -> 55 | K62: =J62*H62 -> 275
F63: =BADA!B33 -> Smart Watch 1 | G63: 1 | H63: =BADA!D33 -> 2 | I63: =SUM(C63*C$37+E63*E$37+G63*G$37) -> 3 | J63: =BADA!E33 -> 80 | K63: =J63*H63 -> 160
F64: =BADA!B34 -> Smart watch 2 | G64: 1 | H64: =BADA!D34 -> 2 | I64: =SUM(C64*C$37+E64*E$37+G64*G$37) -> 3 | J64: 158 | K64: =J64*H64 -> 316
F65: Total | H65: =SUM(H39:H64) -> 478 | J65: =SUM(J39:J64) -> 1221.5 | K65: =SUM(K39:K64) -> 16828
B66: Costos | D66: P MBM | E66: PRV | F66: PVF
B67: =F39 -> B V8 USB | C67: =J39 -> 5 | D67: 20 | E67: =BADA!G9 -> 13 | F67: =BADA!H9 -> 20 | H67: Costo | J67: Venta | K67: Para arranque
B68: =F40 -> B USB - C | C68: =J40 -> 8 | D68: 25 | E68: =BADA!G10 -> 15 | F68: =BADA!H10 -> 25 | G68: Starter | H68: =C93 | J68: =H108 -> 547.5
B69: =F41 -> P USB - C Mot | C69: =J41 -> 20 | D69: 50 | E69: =BADA!G11 -> 30 | F69: =BADA!H11 -> 60 | G69: Advance | H69: =D93 | J69: =H134 -> 1595.5
B70: =F42 -> P C-C Sam | C70: =J42 -> 20 | D70: 50 | E70: =BADA!G12 -> 40 | F70: =BADA!H12 -> 80 | G70: Premium | H70: =E93 | J70: =H164 -> 2133.5
B71: =F43 -> P C-C iP | C71: =J43 -> 11 | D71: 50 | E71: =BADA!G13 -> 40 | F71: =BADA!H13 -> 70
B72: =F44 -> B iPh L | C72: =J44 -> 5.5 | D72: 40 | E72: =BADA!G14 -> 20 | F72: =BADA!H14 -> 35
B73: =F45 -> Cubo iPhone | C73: =J45 -> 20 | D73: 60 | E73: =BADA!G15 -> 40 | F73: =BADA!H15 -> 80 | H73: MBM PAQUETES
B74: =F46 -> P iPh C-L | C74: =J46 -> 29 | D74: 100 | E74: =BADA!G16 -> 40 | F74: =BADA!H16 -> 80
B75: =F47 -> Cubo medio | C75: =J47 -> 20 | D75: 50 | E75: =BADA!G17 -> 30 | F75: =BADA!H17 -> 50 | H75: PAQUETE 1
B76: =F48 -> B Charg Comp C | C76: =J48 -> 28 | D76: 50 | E76: =BADA!G18 -> 40 | F76: =BADA!H18 -> 50 | H76: ACCESORIO | I76: CANTIDAD | J76: COSTO | K76: VENTA TOTAL | L76: UTLD | M76: Reventa | N76: Ganancia
B77: =F49 -> P Charg comp C | C77: =J49 -> 45 | D77: 120 | E77: =BADA!G19 -> 60 | F77: =BADA!H19 -> 130 | H77: Airpod Pro 3 | I77: 3 | J77: 250 | K77: =J77*I77 -> 750 | L77: =K77-(BADA!E25*I77) -> 300 | M77: 400 | N77: =M77*I77 -> 1200
B78: =F50 -> B Charg iPhone L | C78: =J50 | E78: =BADA!G20 -> 15 | F78: =BADA!H20 | H78: Cargador iPh C-L | I78: 1 | J78: 50 | K78: =J78*I78 -> 50 | L78: =J78-BADA!E21 -> 19 | M78: 150 | N78: =M78*I78 -> 150
B79: =F51 -> P Charg iPhone C-L | C79: =J51 -> 31 | D79: 80 | E79: =BADA!G21 -> 45 | F79: =BADA!H21 -> 100 | H79: Cubo iPhone | I79: 1 | J79: 50 | K79: =J79*I79 -> 50 | L79: =K79-BADA!D15 -> 0 | M79: 120 | N79: =M79*I79 -> 120
B80: =F52 -> Bocina 01 | C80: =J52 -> 45 | D80: 100 | E80: =BADA!G22 -> 70 | F80: =BADA!H22 -> 100 | H80: P Cable iPh L | I80: 2 | J80: 40 | K80: =J80*I80 -> 80 | L80: =K80-(BADA!E13*I80) -> 58 | M80: 120 | N80: =M80*I80 -> 240
B81: =F53 -> Bocina 02 | C81: =J53 -> 80 | D81: 150 | E81: =BADA!G23 -> 100 | F81: =BADA!H23 -> 200 | H81: P Cable iPh C | I81: 2 | J81: 50 | K81: =J81*I81 -> 100 | L81: =K81-(BADA!E16*I81) -> 42 | M81: 120 | N81: =M81*I81 -> 240
B82: =F54 -> Audifono Eco | C82: =J54 -> 21 | D82: 80 | E82: =BADA!G24 -> 60 | F82: =BADA!H24 -> 100 | H82: Total | I82: =SUM(I77:I81) -> 9 | J82: =SUM(J77:J81) -> 440 | K82: =SUM(K77:K81) -> 1030 | L82: =SUM(L77:L81) -> 419 | M82: =SUM(M77:M81) -> 910 | N82: =SUM(N77:N81) -> 1950 | O82: =N82-K82 -> 920
B83: =F55 -> Airpods Pro 3 | C83: =J55 -> 150 | D83: 250 | E83: =BADA!G25 -> 250 | F83: =BADA!H25 -> 350
B84: =F56 -> Adaptador 4 en 1 | C84: =J56 -> 17 | D84: 50 | E84: =BADA!G26 -> 45 | F84: =BADA!H26 -> 80
B85: =F57 -> Bluetooth Aux | C85: =J57 -> 18 | D85: 40 | E85: =BADA!G27 -> 25 | F85: =BADA!H27 -> 60
B86: =F58 -> Bocina go 4 | C86: =J58 -> 95 | D86: 150 | E86: =BADA!G28 -> 150 | F86: =BADA!H28 -> 250
B87: =F59 -> Bocina lip 6 | C87: =J59 -> 210 | D87: 300 | E87: =BADA!G29 -> 250 | F87: =BADA!H29 -> 500
B88: =F60 -> Car Charg | C88: =J60 -> 5 | D88: 55 | E88: =BADA!G30 -> 15 | F88: =BADA!H30 -> 55
B89: =F61 -> Transmisor | C89: =J61 -> 45 | D89: 80 | E89: =BADA!G31 -> 60 | F89: =BADA!H31 -> 100
B90: =F62 -> Powerbank | C90: =J62 -> 55 | D90: 100 | E90: =BADA!G32 -> 80 | F90: =BADA!H32 -> 150
B91: =F63 -> Smart Watch 1 | C91: =J63 -> 80 | D91: 150 | E91: =BADA!G33 -> 120 | F91: =BADA!H33 -> 180
B92: =F64 -> Smart watch 2 | C92: =J64 -> 158 | D92: 250 | E92: =BADA!G34 -> 200 | F92: =BADA!H34 -> 300
B93: Total
C94: Starter | D94: Advance | E94: Premium
H96: Ganancia MB
B97: Paquete SARTER | C97: Cantidad | D97: Costo | E97: Precio sugerido | F97: Ganancia
B98: =B67 -> B V8 USB | C98: =C39 -> 1 | D98: =D67 -> 20 | E98: 60 | F98: =(E98-D98)*C98 -> 40 | H98: =(D98-J39)*C98 -> 15
B99: =B68 -> B USB - C | C99: =C40 -> 3 | D99: =D68 -> 25 | E99: 75 | F99: =(E99-D99)*C99 -> 150 | H99: =(D99-J40)*C99 -> 51
B100: =B69 -> P USB - C Mot | C100: =C41 -> 1 | D100: =D69 -> 50 | E100: 90 | F100: =(E100-D100)*C100 -> 40 | H100: =(D100-J41)*C100 -> 30
B101: =B70 -> P C-C Sam | C101: =C42 -> 1 | D101: =D70 -> 50 | E101: 80 | F101: =(E101-D101)*C101 -> 30 | H101: =(D101-J42)*C101 -> 30
B102: =B71 -> P C-C iP | C102: =C43 -> 2 | D102: =D71 -> 50 | E102: 120 | F102: =(E102-D102)*C102 -> 140 | H102: =(D102-J43)*C102 -> 78
B103: =B72 -> B iPh L | C103: =C44 -> 3 | D103: =D72 -> 40 | E103: 100 | F103: =(E103-D103)*C103 -> 180 | H103: =(D103-J44)*C103 -> 103.5
B104: =B73 -> Cubo iPhone | C104: =C45 -> 3 | D104: =D73 -> 60 | E104: 120 | F104: =(E104-D104)*C104 -> 180 | H104: =(D104-J45)*C104 -> 120
B105: =B74 -> P iPh C-L | C105: =C46 | F105: =(E105-D105)*C105 -> 0 | H105: =(D105-J46)*C105 -> 0
B106: =B75 -> Cubo medio | C106: =C47 -> 4 | D106: =D75 -> 50 | E106: 100 | F106: =(E106-D106)*C106 -> 200 | H106: =(D106-J47)*C106 -> 120
C107: =C48 | H107: =(D107-J48)*C107 -> 0
B108: Total | C108: =SUM(C98:C107) -> 18 | D108: =SUM(D98:D107) -> 345 | E108: =SUM(E98:E107) -> 745 | F108: =SUM(F98:F107) -> 960 | H108: =SUM(H98:H107) -> 547.5
H109: Ganancia MB
B110: Paquete ADVANCE | C110: Cantidad | D110: Costo | E110: Precio sugerido | F110: Ganancia
B111: =D39 -> B V8 USB | C111: =E39 -> 2 | D111: =D67 -> 20 | E111: 60 | F111: =(E111-D111)*C111 -> 80 | H111: =(D111-J39)*C111 -> 30
...

Sheet LP
C3: ACCESORIOS MB VALPA | F3: LISTA DE PRECIOS SUGERIDOS
C4: Valparaíso Zacatecas México
C5: Cel: 457 103 2866
B8: PRODUCTO | C8: DESCRIPCIÓN | D8: $ SUGERIDO | E8: $ MAXIMO SUG.
B9: =BADA!B9 -> B V8 USB | C9: =BADA!C9 -> CABLE USB NORMAL TRENZADO SIN CAJA | D9: =DESARROLLO!E138 -> 60 | E9: 80
B10: =BADA!B10 -> B USB - C | C10: CABLE USB TIPO C | D10: =DESARROLLO!E139 -> 75 | E10: 100
B11: =BADA!B11 -> P USB - C Mot | C11: CABLE ORIGINAL TIPO C MOTOROLA | D11: =DESARROLLO!E140 -> 90 | E11: 120
B12: =BADA!B12 -> P C-C Sam | C12: CABLE ORIGINAL TIPO C SAMSUNG | D12: =DESARROLLO!E141 -> 90 | E12: 120
B13: =BADA!B13 -> P C-C iP | C13: CABLE ORIGINAL IPHONE TIPO C | D13: =DESARROLLO!E142 -> 120 | E13: 150
B14: =BADA!B14 -> B iPh L | C14: CABLE IPHONE | D14: =DESARROLLO!E143 -> 100 | E14: 150
B15: =BADA!B15 -> Cubo iPhone | C15: CUBO CARGADOR ORIGINAL IPHONE | D15: =DESARROLLO!E144 -> 120 | E15: 150
B16: =BADA!B16 -> P iPh C-L | C16: CARGDOR IPHONE ORIGINAL | D16: 150 | E16: 200
B17: =BADA!B17 -> Cubo medio | C17: CARGADOR GENERICO CARGA RAPIDA | D17: =DESARROLLO!E146 -> 100 | E17: 150
B18: =BADA!B18 -> B Charg Comp C | C18: CARGADOR 1 HORA TIPO C | D18: =DESARROLLO!E147 -> 80 | E18: 150
B19: =BADA!B19 -> P Charg comp C | C19: CARGADOR ORIGINAL SAMSUNG | D19: =DESARROLLO!E148 -> 180 | E19: 250
B20: =BADA!B20 -> B Charg iPhone L | C20: CARGADOR ECONOMICO IPHONE | D20: 80 | E20: 150
B21: =BADA!B21 -> P Charg iPhone C-L | C21: CARGADOR ORIGINAL IPHONE LIGTHNING | D21: =DESARROLLO!E150 -> 150 | E21: 250
B22: =BADA!B22 -> Bocina 01 | C22: BOCINA GENERICA CHICA | D22: =DESARROLLO!E151 -> 150 | E22: 250
B23: =BADA!B23 -> Bocina 02 | C23: BOCINA GENERICA GRANDE | D23: =DESARROLLO!E152 -> 200 | E23: 300
B24: =BADA!B24 -> Audifono Eco | C24: AUDIFONOS BLUETOOTH | D24: =DESARROLLO!E153 -> 120 | E24: 180
B25: =BADA!B25 -> Airpods Pro 3 | C25: AUDIFONOS ORIGINALES IPHONE | D25: =DESARROLLO!E154 -> 450 | E25: 600
B26: =BADA!B26 -> Adaptador 4 en 1 | C26: ADAPTADOR CABLE TODO TIPO | D26: =DESARROLLO!E155 -> 100 | E26: 200
B27: =BADA!B27 -> Bluetooth Aux | C27: AUXILIAR BLUETOOTH | D27: =DESARROLLO!E156 -> 80 | E27: 150
B28: =BADA!B28 -> Bocina go 4 | C28: BOCINA JBL CHICA | D28: =DESARROLLO!E157 -> 250 | E28: 350
B29: =BADA!B29 -> Bocina lip 6 | C29: BOCINA JBL GRANDE | D29: =DESARROLLO!E158 -> 450 | E29: 600
B30: =BADA!B30 -> Car Charg | C30: CARGADOR CARRO | D30: =DESARROLLO!E159 -> 120 | E30: 200
B31: =BADA!B31 -> Transmisor | C31: TRANSMISOR DE CARRO | D31: =DESARROLLO!E160 -> 120 | E31: 200
B32: =BADA!B32 -> Powerbank | C32: POWERBANK O BATERIA EXTERNA | D32: =DESARROLLO!E161 -> 150 | E32: 250
... B34: =BADA!B34 -> Smart watch 2 | C34: RELOJ INTELIGENTE COMBO | D34: =DESARROLLO!E163 -> 350 | E34: 500

Sheet FRM
D4: ACCESORIOS MB VALPA
D5: Zacatecas México
D6: Cel: 457 103 2866
F7: Formato de resguardo de mercancia
C8: Datos generales
C9: Fecha
C10: Paquete
C11: Lugar
C12: Promotor
C14: FECHA
B15: # | C15: Concepto
B16: 1 | C16: =BADA!B9 -> B V8 USB
B17: 2 | C17: =BADA!B10 -> B USB - C
B18: 3 | C18: =BADA!B11 -> P USB - C Mot
B19: 4 | C19: =BADA!B12 -> P C-C Sam
B20: 5 | C20: =BADA!B13 -> P C-C iP
B21: 6 | C21: =BADA!B14 -> B iPh L
B22: 7 | C22: =BADA!B15 -> Cubo iPhone
B23: 8 | C23: =BADA!B16 -> P iPh C-L
B24: 9 | C24: =BADA!B17 -> Cubo medio
B25: 10 | C25: =BADA!B18 -> B Charg Comp C
B26: 11 | C26: =BADA!B19 -> P Charg comp C
B27: 12 | C27: =BADA!B20 -> B Charg iPhone L
... B41: 26 | C41: =BADA!B34 -> Smart watch 2
B42: 27
C43: TOTAL
C45: Por medio del pressente estoy conforme con la mercancia así como el resguardo de la misma.
C47: Nombre y firma del r. negocio | F47: Nombre y firma del promotor

Sheet AMB
C3: CELULARES MB VALPA | F3: RELACION DE ACCESORIOS VENDIDOS
C4: Valparaíso Zacatecas México
C5: Cel: 457 103 2866
B8: CODIGO | C8: DESCRIPCIÓN | D8: Stock Inicial | E8: 46130 | F8: 46131 | G8: 46132 | M8: TOTAL
B9: =BADA!B9 -> B V8 USB | C9: =BADA!C9 -> CABLE USB NORMAL TRENZADO SIN CAJA | D9: =BADA!D9 -> 20 | M9: =D9-E9-F9-G9-H9-I9-J9-K9-L9 -> 20
B10: =BADA!B10 -> B USB - C | C10: =BADA!C10 -> CABLE USB TIPO C TRENZADO SIN CAJA | D10: =BADA!D10 -> 40 | M10: =D10-E10-F10-G10-H10-I10-J10-K10-L10 -> 40
B11: =BADA!B11 -> P USB - C Mot | C11: =BADA!C11 -> CABLE ORIGINAL USB A C MOTOROLA | D11: =BADA!D11 -> 20 | M11: =D11-E11-F11-G11-H11-I11-J11-K11-L11 -> 20
B12: =BADA!B12 -> P C-C Sam | C12: =BADA!C12 -> CABLE ORIGINAL TIPO C-C SAMSUNG | D12: =BADA!D12 -> 20 | M12: =D12-E12-F12-G12-H12-I12-J12-K12-L12 -> 20
B13: =BADA!B13 -> P C-C iP | C13: =BADA!C13 -> CABLE ORIGINAL IPHONE TIPO C | D13: =BADA!D13 -> 30 | M13: =D13-E13-F13-G13-H13-I13-J13-K13-L13 -> 30
B14: =BADA!B14 -> B iPh L | C14: =BADA!C14 -> CABLE IPHONE C A LIGTHNING | D14: =BADA!D14 -> 40 | M14: =D14-E14-F14-G14-H14-I14-J14-K14-L14 -> 40
B15: =BADA!B15 -> Cubo iPhone | C15: =BADA!C15 -> CUBO 20W ORIGINAL IPHONE | D15: =BADA!D15 -> 50 | M15: =D15-E15-F15-G15-H15-I15-J15-K15-L15 -> 50
B16: =BADA!B16 -> P iPh C-L | C16: =BADA!C16 -> CARGDOR IPHONE ORIGINAL C-LIGTH | D16: =BADA!D16 -> 15 | F16: 2 | M16: =D16-E16-F16-G16-H16-I16-J16-K16-L16 -> 13
B17: =BADA!B17 -> Cubo medio | C17: =BADA!C17 -> CARGADOR GEN12W USB + C Sin CAJA | D17: =BADA!D17 -> 52 | M17: =D17-E17-F17-G17-H17-I17-J17-K17-L17 -> 52
B18: =BADA!B18 -> B Charg Comp C | C18: =BADA!C18 -> CARGADOR COMPLETO 1 HORA TIPO C | D18: =BADA!D18 -> 10 | M18: =D18-E18-F18-G18-H18-I18-J18-K18-L18 -> 10
B19: =BADA!B19 -> P Charg comp C | C19: =BADA!C19 -> CARGADOR ORIGINAL SAMSUNG USB-C | D19: =BADA!D19 -> 10 | F19: 1 | M19: =D19-E19-F19-G19-H19-I19-J19-K19-L19 -> 9
B20: =BADA!B20 -> B Charg iPhone L | C20: =BADA!C20 -> CARGADOR ECONOMICO IPHONE | D20: =BADA!D20 -> 40 | M20: =D20-E20-F20-G20-H20-I20-J20-K20-L20 -> 40
B21: =BADA!B21 -> P Charg iPhone C-L | C21: =BADA!C21 -> CARGADOR ORIGINAL IPHONE LIGTHNING | D21: =BADA!D21 -> 10 | M21: =D21-E21-F21-G21-H21-I21-J21-K21-L21 -> 10
B22: =BADA!B22 -> Bocina 01 | C22: =BADA!C22 -> BOCINA GENERICA CHICA | D22: =BADA!D22 -> 2 | M22: =D22-E22-F22-G22-H22-I22-J22-K22-L22 -> 2
B23: =BADA!B23 -> Bocina 02 | C23: =BADA!C23 -> BOCINA GENERICA MEDIANA | D23: =BADA!D23 -> 2 | M23: =D23-E23-F23-G23-H23-I23-J23-K23-L23 -> 2
B24: =BADA!B24 -> Audifono Eco | C24: =BADA!C24 -> AUDIFONOS BLUETOOTH GENERICOS | D24: =BADA!D24 -> 18 | E24: 1 | M24: =D24-E24-F24-G24-H24-I24-J24-K24-L24 -> 17
B25: =BADA!B25 -> Airpods Pro 3 | C25: =BADA!C25 -> AIRPODS PRO 3 CANCELACION GPS #SERIE | D25: =BADA!D25 -> 50 | E25: 3 | M25: =D25-E25-F25-G25-H25-I25-J25-K25-L25 -> 47
B26: =BADA!B26 -> Adaptador 4 en 1 | C26: =BADA!C26 -> ADAPTADOR CABLE 4 EN 1 | D26: =BADA!D26 -> 10 | M26: =D26-E26-F26-G26-H26-I26-J26-K26-L26 -> 10
B27: =BADA!B27 -> Bluetooth Aux | C27: =BADA!C27 -> AUXILIAR BLUETOOTH | D27: =BADA!D27 -> 3 | M27: =D27-E27-F27-G27-H27-I27-J27-K27-L27 -> 3
B28: =BADA!B28 -> Bocina go 4 | C28: =BADA!C28 -> BOCINA JBL CHICA GO 4 | D28: =BADA!D28 -> 12 | M28: =D28-E28-F28-G28-H28-I28-J28-K28-L28 -> 12
B29: =BADA!B29 -> Bocina lip 6 | C29: =BADA!C29 -> BOCINA JBL GRANDE FLIP 6 | D29: =BADA!D29 -> 5 | M29: =D29-E29-F29-G29-H29-I29-J29-K29-L29 -> 5
B30: =BADA!B30 -> Car Charg | C30: =BADA!C30 -> CARGADOR CARRO | D30: =BADA!D30 -> 5 | M30: =D30-E30-F30-G30-H30-I30-J30-K30-L30 -> 5
B31: =BADA!B31 -> Transmisor | C31: =BADA!C31 -> TRANSMISOR DE CARRO | D31: =BADA!D31 -> 5 | M31: =D31-E31-F31-G31-H31-I31-J31-K31-L31 -> 5
B32: =BADA!B32 -> Powerbank | C32: =BADA!C32 -> POWERBANK 20,000 Ma | D32: =BADA!D32 -> 5 | M32: =D32-E32-F32-G32-H32-I32-J32-K32-L32 -> 5
B33: =BADA!B33 -> Smart Watch 1 | C33: =BADA!C33 -> RELOJ INTELIGENTE | D33: =BADA!D33 -> 2 | E33: 1 | M33: =D33-E33-F33-G33-H33-I33-J33-K33-L33 -> 1
B34: =BADA!B34 -> Smart watch 2 | C34: =BADA!C34 -> RELOJ INTELIGENTE COMBO | D34: =BADA!D34 -> 2 | M34: =D34-E34-F34-G34-H34-I34-J34-K34-L34 -> 2
B36: =BADA!B36
B42: CODIGO | C42: DESCRIPCIÓN | D42: Stock Inicial | E42: 46130 | F42: 46131 | G42: 46132 | M42: TOTAL
B43: =BADA!B9 -> B V8 USB | C43: =BADA!C9 -> CABLE USB NORMAL TRENZADO SIN CAJA | D43: =BADA!D9 -> 20 | M43: =(E9*E43)+(F9*F43)+G9*G43+H9*H43+I9*I43+J9*J43+K9*K43+L9*L43 -> 0
B44: =BADA!B10 -> B USB - C | C44: =BADA!C10 -> CABLE USB TIPO C TRENZADO SIN CAJA | D44: =BADA!D10 -> 40 | M44: =(E10*E44)+(F10*F44)+G10*G44+H10*H44+I10*I44+J10*J44+K10*K44+L10*L44 -> 0
B45: =BADA!B11 -> P USB - C Mot | C45: =BADA!C11 -> CABLE ORIGINAL USB A C MOTOROLA | D45: =BADA!D11 -> 20 | M45: =(E11*E45)+(F11*F45)+G11*G45+H11*H45+I11*I45+J11*J45+K11*K45+L11*L45 -> 0
B46: =BADA!B12 -> P C-C Sam | C46: =BADA!C12 -> CABLE ORIGINAL TIPO C-C SAMSUNG | D46: =BADA!D12 -> 20 | M46: =(E12*E46)+(F12*F46)+G12*G46+H12*H46+I12*I46+J12*J46+K12*K46+L12*L46 -> 0
B47: =BADA!B13 -> P C-C iP | C47: =BADA!C13 -> CABLE ORIGINAL IPHONE TIPO C | D47: =BADA!D13 -> 30 | M47: =(E13*E47)+(F13*F47)+G13*G47+H13*H47+I13*I47+J13*J47+K13*K47+L13*L47 -> 0
B48: =BADA!B14 -> B iPh L | C48: =BADA!C14 -> CABLE IPHONE C A LIGTHNING | D48: =BADA!D14 -> 40 | M48: =(E14*E48)+(F14*F48)+G14*G48+H14*H48+I14*I48+J14*J48+K14*K48+L14*L48 -> 0
B49: =BADA!B15 -> Cubo iPhone | C49: =BADA!C15 -> CUBO 20W ORIGINAL IPHONE | D49: =BADA!D15 -> 50 | M49: =(E15*E49)+(F15*F49)+G15*G49+H15*H49+I15*I49+J15*J49+K15*K49+L15*L49 -> 0
B50: =BADA!B16 -> P iPh C-L | C50: =BADA!C16 -> CARGDOR IPHONE ORIGINAL C-LIGTH | D50: =BADA!D16 -> 15 | M50: =(E16*E50)+(F16*F50)+G16*G50+H16*H50+I16*I50+J16*J50+K16*K50+L16*L50 -> 0
B51: =BADA!B17 -> Cubo medio | C51: =BADA!C17 -> CARGADOR GEN12W USB + C Sin CAJA | D51: =BADA!D17 -> 52 | M51: =(E17*E51)+(F17*F51)+G17*G51+H17*H51+I17*I51+J17*J51+K17*K51+L17*L51 -> 0
B52: =BADA!B18 -> B Charg Comp C | C52: =BADA!C18 -> CARGADOR COMPLETO 1 HORA TIPO C | D52: =BADA!D18 -> 10 | M52: =(E18*E52)+(F18*F52)+G18*G52+H18*H52+I18*I52+J18*J52+K18*K52+L18*L52 -> 0
B53: =BADA!B19 -> P Charg comp C | C53: =BADA!C19 -> CARGADOR ORIGINAL SAMSUNG USB-C | D53: =BADA!D19 -> 10 | F53: 180 | M53: =(E19*E53)+(F19*F53)+G19*G53+H19*H53+I19*I53+J19*J53+K19*K53+L19*L53 -> 180
B54: =BADA!B20 -> B Charg iPhone L | C54: =BADA!C20 -> CARGADOR ECONOMICO IPHONE | D54: =BADA!D20 -> 40 | M54: =(E20*E54)+(F20*F54)+G20*G54+H20*H54+I20*I54+J20*J54+K20*K54+L20*L54 -> 0
B55: =BADA!B21 -> P Charg iPhone C-L | C55: =BADA!C21 -> CARGADOR ORIGINAL IPHONE LIGTHNING | D55: =BADA!D21 -> 10 | F55: 200 | M55: =(E21*E55)+(F21*F55)+G21*G55+H21*H55+I21*I55+J21*J55+K21*K55+L21*L55 -> 0
B56: =BADA!B22 -> Bocina 01 | C56: =BADA!C22 -> BOCINA GENERICA CHICA | D56: =BADA!D22 -> 2 | M56: =(E22*E56)+(F22*F56)+G22*G56+H22*H56+I22*I56+J22*J56+K22*K56+L22*L56 -> 0
B57: =BADA!B23 -> Bocina 02 | C57: =BADA!C23 -> BOCINA GENERICA MEDIANA | D57: =BADA!D23 -> 2 | M57: =(E23*E57)+(F23*F57)+G23*G57+H23*H57+I23*I57+J23*J57+K23*K57+L23*L57 -> 0
B58: =BADA!B24 -> Audifono Eco | C58: =BADA!C24 -> AUDIFONOS BLUETOOTH GENERICOS | D58: =BADA!D24 -> 18 | E58: 100 | M58: =(E24*E58)+(F24*F58)+G24*G58+H24*H58+I24*I58+J24*J58+K24*K58+L24*L58 -> 100
B59: =BADA!B25 -> Airpods Pro 3 | C59: =BADA!C25 -> AIRPODS PRO 3 CANCELACION GPS #SERIE | D59: =BADA!D25 -> 50 | E59: 250 | M59: =(E25*E59)+(F25*F59)+G25*G59+H25*H59+I25*I59+J25*J59+K25*K59+L25*L59 -> 750
B60: =BADA!B26 -> Adaptador 4 en 1 | C60: =BADA!C26 -> ADAPTADOR CABLE 4 EN 1 | D60: =BADA!D26 -> 10 | M60: =(E26*E60)+(F26*F60)+G26*G60+H26*H60+I26*I60+J26*J60+K26*K60+L26*L60 -> 0
B61: =BADA!B27 -> Bluetooth Aux | C61: =BADA!C27 -> AUXILIAR BLUETOOTH | D61: =BADA!D27 -> 3 | M61: =(E27*E61)+(F27*F61)+G27*G61+H27*H61+I27*I61+J27*J61+K27*K61+L27*L61 -> 0
B62: =BADA!B28 -> Bocina go 4 | C62: =BADA!C28 -> BOCINA JBL CHICA GO 4 | D62: =BADA!D28 -> 12 | M62: =(E28*E62)+(F28*F62)+G28*G62+H28*H62+I28*I62+J28*J62+K28*K62+L28*L62 -> 0
B63: =BADA!B29 -> Bocina lip 6 | C63: =BADA!C29 -> BOCINA JBL GRANDE FLIP 6 | D63: =BADA!D29 -> 5 | M63: =(E29*E63)+(F29*F63)+G29*G63+H29*H63+I29*I63+J29*J63+K29*K63+L29*L63 -> 0
B64: =BADA!B30 -> Car Charg | C64: =BADA!C30 -> CARGADOR CARRO | D64: =BADA!D30 -> 5 | M64: =(E30*E64)+(F30*F64)+G30*G64+H30*H64+I30*I64+J30*J64+K30*K64+L30*L64 -> 0
B65: =BADA!B31 -> Transmisor | C65: =BADA!C31 -> TRANSMISOR DE CARRO | D65: =BADA!D31 -> 5 | M65: =(E31*E65)+(F31*F65)+G31*G65+H31*H65+I31*I65+J31*J65+K31*K65+L31*L65 -> 0
B66: =BADA!B32 -> Powerbank | C66: =BADA!C32 -> POWERBANK 20,000 Ma | D66: =BADA!D32 -> 5 | M66: =(E32*E66)+(F32*F66)+G32*G66+H32*H66+I32*I66+J32*J66+K32*K66+L32*L66 -> 0
B67: =BADA!B33 -> Smart Watch 1 | C67: =BADA!C33 -> RELOJ INTELIGENTE | D67: =BADA!D33 -> 2 | E67: 250 | M67: =(E33*E67)+(F33*F67)+G33*G67+H33*H67+I33*I67+J33*J67+K33*K67+L33*L67 -> 250
B68: =BADA!B34 -> Smart watch 2 | C68: =BADA!C34 -> RELOJ INTELIGENTE COMBO | D68: =BADA!D34 -> 2 | M68: =(E34*E68)+(F34*F68)+G34*G68+H34*H68+I34*I68+J34*J68+K34*K68+L34*L68 -> 0

Sheet PDF MAYOREO
C5: Datos generales
C6: Fecha | D6: 46134
B9: # | C9: Concepto | D9: DESCRIPCIÓN | E9: PRECIO | G9: COMENT
B10: 1 | C10: =BADA!B9 -> B V8 USB | D10: =BADA!C9 -> CABLE USB NORMAL TRENZADO SIN CAJA | E10: =BADA!G9 -> 13 | G10: El color podria variar
B11: 2 | C11: =BADA!B10 -> B USB - C | D11: =BADA!C10 -> CABLE USB TIPO C TRENZADO SIN CAJA | E11: =BADA!G10 -> 15 | G11: El color podria variar
B12: 3 | C12: =BADA!B11 -> P USB - C Mot | D12: =BADA!C11 -> CABLE ORIGINAL USB A C MOTOROLA | E12: =BADA!G11 -> 30
B13: 4 | C13: =BADA!B12 -> P C-C Sam | D13: =BADA!C12 -> CABLE ORIGINAL TIPO C-C SAMSUNG | E13: =BADA!G12 -> 40
B14: 5 | C14: =BADA!B13 -> P C-C iP | D14: =BADA!C13 -> CABLE ORIGINAL IPHONE TIPO C | E14: =BADA!G13 -> 40
B15: 6 | C15: =BADA!B14 -> B iPh L | D15: =BADA!C14 -> CABLE IPHONE C A LIGTHNING | E15: =BADA!G14 -> 20
B16: 7 | C16: =BADA!B15 -> Cubo iPhone | D16: =BADA!C15 -> CUBO 20W ORIGINAL IPHONE | E16: =BADA!G15 -> 40
B17: 8 | C17: =BADA!B16 -> P iPh C-L | D17: =BADA!C16 -> CARGDOR IPHONE ORIGINAL C-LIGTH | E17: =BADA!G16 -> 40
B18: 9 | C18: =BADA!B17 -> Cubo medio | D18: =BADA!C17 -> CARGADOR GEN12W USB + C Sin CAJA | E18: =BADA!G17 -> 30
B19: 10 | C19: =BADA!B18 -> B Charg Comp C | D19: =BADA!C18 -> CARGADOR COMPLETO 1 HORA TIPO C | E19: =BADA!G18 -> 40
B20: 11 | C20: =BADA!B19 -> P Charg comp C | D20: =BADA!C19 -> CARGADOR ORIGINAL SAMSUNG USB-C | E20: =BADA!G19 -> 60
B21: 12 | C21: =BADA!B20 -> B Charg iPhone L | D21: =BADA!C20 -> CARGADOR ECONOMICO IPHONE | E21: =BADA!G20 -> 15
B22: 13 | C22: =BADA!B21 -> P Charg iPhone C-L | D22: =BADA!C21 -> CARGADOR ORIGINAL IPHONE LIGTHNING | E22: =BADA!G21 -> 45
B23: 14 | C23: =BADA!B22 -> Bocina 01 | D23: =BADA!C22 -> BOCINA GENERICA CHICA | E23: =BADA!G22 -> 70
B24: 15 | C24: =BADA!B23 -> Bocina 02 | D24: =BADA!C23 -> BOCINA GENERICA MEDIANA | E24: =BADA!G23 -> 100
B25: 16 | C25: =BADA!B24 -> Audifono Eco | D25: =BADA!C24 -> AUDIFONOS BLUETOOTH GENERICOS | E25: =BADA!G24 -> 60 | G25: El modelo podria variar
B26: 17 | C26: =BADA!B25 -> Airpods Pro 3 | D26: =BADA!C25 -> AIRPODS PRO 3 CANCELACION GPS #SERIE | E26: =BADA!G25 -> 250 | G26: Alta caliadad, cancelación de ruido, GPS , Número de serie Apple, Carga inalambrica, Traductor
B27: 18 | C27: =BADA!B26 -> Adaptador 4 en 1 | D27: =BADA!C26 -> ADAPTADOR CABLE 4 EN 1 | E27: =BADA!G26 -> 45
B28: 19 | C28: =BADA!B27 -> Bluetooth Aux | D28: =BADA!C27 -> AUXILIAR BLUETOOTH | E28: =BADA!G27 -> 25
B29: 20 | C29: =BADA!B28 -> Bocina go 4 | D29: =BADA!C28 -> BOCINA JBL CHICA GO 4 | E29: =BADA!G28 -> 150 | G29: El color podria variar
B30: 21 | C30: =BADA!B29 -> Bocina lip 6 | D30: =BADA!C29 -> BOCINA JBL GRANDE FLIP 6 | E30: =BADA!G29 -> 250 | G30: El color podria variar
B31: 22 | C31: =BADA!B30 -> Car Charg | D31: =BADA!C30 -> CARGADOR CARRO | E31: =BADA!G30 -> 15
B32: 23 | C32: =BADA!B31 -> Transmisor | D32: =BADA!C31 -> TRANSMISOR DE CARRO | E32: =BADA!G31 -> 60 | G32: El modelo podria variar
B33: 24 | C33: =BADA!B32 -> Powerbank | D33: =BADA!C32 -> POWERBANK 20,000 Ma | E33: =BADA!G32 -> 80
B34: 25 | C34: =BADA!B33 -> Smart Watch 1 | D34: =BADA!C33 -> RELOJ INTELIGENTE | E34: =BADA!G33 -> 120 | G34: Agotado
B35: 26 | C35: =BADA!B34 -> Smart watch 2 | D35: =BADA!C34 -> RELOJ INTELIGENTE COMBO | E35: =BADA!G34 -> 200 | G35: Agotado
B36: 27 | C36: =BADA!B38 -> Playera | D36: =BADA!C38 -> Playera Selección Mexicana Verde Mundial | E36: =BADA!G38 -> 100 | G36: Consultar tallas
C37: =BADA!B39 -> Audif Skullc | D37: =BADA!C39 -> SKULLCANDY TWS7 BLUET | E37: =BADA!G39 -> 80
C38: =BADA!B40 -> Audif Earpods B | D38: =BADA!C40 -> EARPODS GENERICOS | E38: =BADA!G40 -> 60
C39: =BADA!B41 -> Audif Buytiti 125 | D39: =BADA!C41 -> AUDIFONOS BLUETOOTH | E39: =BADA!G41 -> 60
C40: =BADA!B42 -> Audif Buy W133 | E40: =BADA!G42 -> 60
C42: TOTAL
